pascman/__init__.py
pascman/__main__.py
pascman-0.0.6.dist-info/LICENSE
pascman-0.0.6.dist-info/METADATA
pascman-0.0.6.dist-info/WHEEL
pascman-0.0.6.dist-info/entry_points.txt
pascman-0.0.6.dist-info/top_level.txt
pascman-0.0.6.dist-info/RECORD
