Metadata-Version: 2.1
Name: pascman
Version: 0.0.6
Summary: Eat every text that you want with this simpatic pacman! :D
Home-page: https://github.com/Ronald-TR/pascman
Author: Ronald Rodrigues Farias
Author-email: ronald-farias@outlook.com
License: UNKNOWN
Platform: UNKNOWN
Classifier: Programming Language :: Python :: 3
Classifier: License :: OSI Approved :: MIT License
Classifier: Operating System :: OS Independent
